.coveragerc
.pylintrc
MANIFEST.in
README.rst
setup.cfg
setup.py
tox.ini
etc/.Dockerfile.swo
etc/Dockerfile
etc/docker-robottests
etc/docker_cmd
etc/sshd_config
robottests/README.rst
robottests/target_script.sh
robottests/targethosts.py
robottests/test_remotescript.robot
sphinxdocs/CHANGES.rst
sphinxdocs/README.rst
sphinxdocs/conf.py
sphinxdocs/index.rst
sphinxdocs/requirements.txt
sphinxdocs/robotdocs.rst
src/crl/__init__.py
src/crl.remotescript.egg-info/PKG-INFO
src/crl.remotescript.egg-info/SOURCES.txt
src/crl.remotescript.egg-info/dependency_links.txt
src/crl.remotescript.egg-info/entry_points.txt
src/crl.remotescript.egg-info/namespace_packages.txt
src/crl.remotescript.egg-info/requires.txt
src/crl.remotescript.egg-info/top_level.txt
src/crl/remotescript/FP.py
src/crl/remotescript/RemoteScript.py
src/crl/remotescript/SSHClientBase.py
src/crl/remotescript/__init__.py
src/crl/remotescript/_version.py
src/crl/remotescript/baseengine.py
src/crl/remotescript/compatibility.py
src/crl/remotescript/connectionmediator.py
src/crl/remotescript/fpengine.py
src/crl/remotescript/pathops.py
src/crl/remotescript/remotefile.py
src/crl/remotescript/result.py
src/crl/remotescript/robotdocsconf.py
src/crl/remotescript/scp.py
src/crl/remotescript/ssh.py
src/crl/remotescript/sshjava.py
src/crl/remotescript/target.py
tests/__init__.py
tests/test_remotescript.py
tests/test_sshclient.py