Metadata-Version: 1.1
Name: crl.remotescript
Version: 1.0.3
Summary: Robot test library for executing shell commands and scripts over SSH and Telnet and transferring files over SFTP, SCP and FTP protocols
Home-page: https://github.com/nokia/crl-remotescript
Author: Zoltán Veres
Author-email: zoltan.veres@nokia.com
License: BSD-3-Clause
Keywords: SSH Telnet SFTP FTP
Platform: UNKNOWN
Classifier: Intended Audience :: Developers
Classifier: License :: OSI Approved :: BSD License
Classifier: Programming Language :: Python :: 2
Classifier: Programming Language :: Python :: 2.7
Classifier: Programming Language :: Python :: 3
Classifier: Programming Language :: Python :: 3.6
Classifier: Programming Language :: Python :: 3.7
Classifier: Topic :: Software Development
